MaquinaDeEstados/fsm_charger.v
module fsm_charger (
    input wire clk,
    // No usamos rst_n físico global, usamos un reset interno + soft_reset
    
    // Entradas (Mapeadas a J1)
    input wire rpm_in_range,            // Sensor RPM
    input wire bat_charged,            // Sensor Batería
    input wire soft_reset,   // Botón externo
    
    // Salidas (Mapeadas a J2-J4)
    output reg L_off,
    output reg L_SEARCH,
    output reg L_TRACK,
    output reg pid_enable,
    output reg servo_force_close
);

    // --- CONFIGURACIÓN DE ESTADOS ---
    parameter S_OFF    = 2'b00;
    parameter S_SEARCH = 2'b01;
    parameter S_TRACK  = 2'b10;

    reg [1:0] current_state = S_OFF;
    reg [1:0] next_state;

    // --- GENERADOR DE RESET INTERNO (POWER-ON RESET) ---
    // Esto asegura que la FPGA inicie en OFF al conectarla
    reg [3:0] reset_count = 0;
    reg internal_reset_active = 1;

    always @(posedge clk) begin
        if (reset_count < 4'd15) begin
            reset_count <= reset_count + 1'b1;
            internal_reset_active <= 1; // Reset activo
        end else begin
            internal_reset_active <= 0; // Soltar reset
        end
    end

    // Señal maestra de reset (Interno O Botón externo)
    wire system_reset = internal_reset_active || soft_reset;

    // --- 1. MEMORIA DE ESTADO ---
    always @(posedge clk) begin
        if (system_reset) begin
            current_state <= S_OFF;
        end else begin
            current_state <= next_state;
        end
    end

    // --- 2. LÓGICA DE SIGUIENTE ESTADO ---
    always @(*) begin
        next_state = current_state; // Valor por defecto

        case (current_state)
            S_OFF: begin
                // PRIORIDAD: Si hay reset o batería llena, nos quedamos en OFF.
                // Si la batería NO está llena (!bat_charged) y no hay reset, pasamos a SEARCH.
                // NOTA: Ignoramos 'r' aquí (seguridad).
                if (bat_charged)      next_state = S_OFF;
                else        next_state = S_SEARCH;
            end

            S_SEARCH: begin
                if (bat_charged)      next_state = S_OFF;   // Batería llena -> Apagar
                else if (rpm_in_range) next_state = S_TRACK; // RPM Estables -> TRACK
                else        next_state = S_SEARCH;// Si no, seguir buscando
            end

            S_TRACK: begin
                if (bat_charged)      next_state = S_OFF;    // Batería llena -> Apagar
                else if (!rpm_in_range) next_state = S_SEARCH; // Perdimos RPM -> Buscar
                else        next_state = S_TRACK;  // Todo OK -> Mantener
            end
            
            default: next_state = S_OFF;
        endcase
    end

    // --- 3. LÓGICA DE SALIDA ---
    always @(*) begin
        // Valores por defecto (Seguridad)
        L_off = 0; L_SEARCH = 0; L_TRACK = 0;
        pid_enable = 0; servo_force_close = 1; 

        case (current_state)
            S_OFF: begin
                L_off             = 1;
                L_SEARCH          = 0;
                L_TRACK           = 0;
                pid_enable        = 0;
                servo_force_close = 1; // Servo cerrado forzosamente
            end

            S_SEARCH: begin
                L_off             = 0;
                L_SEARCH          = 1;
                L_TRACK           = 0;
                pid_enable        = 1; // PID activo para buscar estabilidad
                servo_force_close = 0;
            end

            S_TRACK: begin
                L_off             = 0;
                L_SEARCH          = 0;
                L_TRACK           = 1;
                pid_enable        = 1; // PID activo para mantener (segun tu corrección)
                servo_force_close = 0;
            end
        endcase
    end

endmodule

MaquinaDeEstados/fsm_charger_tb.v
`timescale 1ns / 1ps

module fsm_charger_tb;

    // 1. Declaración de Señales (Inputs como reg, Outputs como wire)
    reg clk;
    reg rpm_in_range;
    reg bat_charged;
    reg soft_reset;

    wire L_off;
    wire L_SEARCH;
    wire L_TRACK;
    wire pid_enable;
    wire servo_force_close;

    // 2. Instanciación de la FSM (Unit Under Test)
    fsm_charger uut (
        .clk(clk),
        .rpm_in_range(rpm_in_range),
        .bat_charged(bat_charged),
        .soft_reset(soft_reset),
        .L_off(L_off),
        .L_SEARCH(L_SEARCH),
        .L_TRACK(L_TRACK),
        .pid_enable(pid_enable),
        .servo_force_close(servo_force_close)
    );

    // 3. Generación del Reloj (25 MHz -> 40ns periodo)
    always #20 clk = ~clk; 

    // 4. Proceso de Prueba
    initial begin
        // A. Inicialización
        $dumpfile("fsm_charger_tb.vcd"); // Archivo para GTKWave
        $dumpvars(0, fsm_charger_tb);
        
        clk = 0;
        rpm_in_range = 0;
        bat_charged = 0;
        soft_reset = 0;

        $display("--- INICIO DE SIMULACION ---");
        $display("Tiempo | Estado | In: RPM / Bat | Out: PID / Servo");

        // B. Esperar el Power-On Reset (Tu lógica tiene un contador de 15 ciclos)
        $display("Esperando reset interno (Power-On)...");
        repeat(20) @(posedge clk); 
        
        // --- PRUEBA 1: ARRANQUE (OFF -> SEARCH) ---
        // La batería NO está cargada (bat=0), debería pasar a SEARCH
        $display("Test 1: Bateria descargada, sistema debe buscar.");
        bat_charged = 0;
        #100; // Esperar unos ciclos

        // --- PRUEBA 2: ENCONTRAR RPM (SEARCH -> TRACK) ---
        // Simulamos que el generador llega a 700 RPM
        $display("Test 2: RPM estables. Pasar a TRACK.");
        rpm_in_range = 1;
        #100;

        // --- PRUEBA 3: PERDIDA DE ESTABILIDAD (TRACK -> SEARCH) ---
        // El viento cae, RPM bajan
        $display("Test 3: RPM inestables. Volver a SEARCH.");
        rpm_in_range = 0;
        #100;

        // --- PRUEBA 4: RECUPERACION (SEARCH -> TRACK) ---
        $display("Test 4: RPM recuperadas. Volver a TRACK.");
        rpm_in_range = 1;
        #100;

        // --- PRUEBA 5: BATERIA LLENA (TRACK -> OFF) ---
        // El BMS dice "Ya basta"
        $display("Test 5: Bateria LLENA. Apagar sistema (OFF).");
        bat_charged = 1;
        #100;

        // --- PRUEBA 6: SEGURIDAD EN OFF ---
        // Aunque haya RPM, si la batería está llena, no debe encender
        $display("Test 6: Intento de arranque con bateria llena (Debe fallar).");
        rpm_in_range = 1; 
        #100;

        // --- PRUEBA 7: DESCARGA DE BATERIA (OFF -> SEARCH) ---
        // La batería se usó, voltaje cae
        $display("Test 7: Bateria se descarga. Reiniciar busqueda.");
        bat_charged = 0;
        #100;

        // --- PRUEBA 8: RESET MANUAL ---
        // Botonazo de emergencia
        $display("Test 8: Boton de Reset presionado.");
        soft_reset = 1;
        #100;
        soft_reset = 0;
        #100;

        $display("--- FIN DE SIMULACION ---");
        $finish;
    end

    // Monitor opcional para ver en consola
    always @(posedge clk) begin
        // Imprime cambios significativos
        // Lógica para detectar cambio de estado visualmente en consola
    end

endmodule

MaquinaDeEstados/sim/fsm_charger_tb.vcd
$date
	Wed Dec 10 11:46:26 2025
$end
$version
	Icarus Verilog
$end
$timescale
	1ps
$end
$scope module fsm_charger_tb $end
$var wire 1 ! servo_force_close $end
$var wire 1 " pid_enable $end
$var wire 1 # L_off $end
$var wire 1 $ L_TRACK $end
$var wire 1 % L_SEARCH $end
$var reg 1 & bat_charged $end
$var reg 1 ' clk $end
$var reg 1 ( rpm_in_range $end
$var reg 1 ) soft_reset $end
$scope module uut $end
$var wire 1 & bat_charged $end
$var wire 1 ' clk $end
$var wire 1 ( rpm_in_range $end
$var wire 1 ) soft_reset $end
$var wire 1 * system_reset $end
$var parameter 2 + S_OFF $end
$var parameter 2 , S_SEARCH $end
$var parameter 2 - S_TRACK $end
$var reg 1 % L_SEARCH $end
$var reg 1 $ L_TRACK $end
$var reg 1 # L_off $end
$var reg 2 . current_state [1:0] $end
$var reg 1 / internal_reset_active $end
$var reg 2 0 next_state [1:0] $end
$var reg 1 " pid_enable $end
$var reg 4 1 reset_count [3:0] $end
$var reg 1 ! servo_force_close $end
$upscope $end
$upscope $end
$enddefinitions $end
$comment Show the parameter values. $end
$dumpall
b10 -
b1 ,
b0 +
$end
#0
$dumpvars
b0 1
b1 0
1/
b0 .
1*
0)
0(
0'
0&
0%
0$
1#
0"
1!
$end
#20000
b1 1
1'
#40000
0'
#60000
b10 1
1'
#80000
0'
#100000
b11 1
1'
#120000
0'
#140000
b100 1
1'
#160000
0'
#180000
b101 1
1'
#200000
0'
#220000
b110 1
1'
#240000
0'
#260000
b111 1
1'
#280000
0'
#300000
b1000 1
1'
#320000
0'
#340000
b1001 1
1'
#360000
0'
#380000
b1010 1
1'
#400000
0'
#420000
b1011 1
1'
#440000
0'
#460000
b1100 1
1'
#480000
0'
#500000
b1101 1
1'
#520000
0'
#540000
b1110 1
1'
#560000
0'
#580000
b1111 1
1'
#600000
0'
#620000
0*
0/
1'
#640000
0'
#660000
0!
1"
1%
0#
b1 .
1'
#680000
0'
#700000
1'
#720000
0'
#740000
1'
#760000
0'
#780000
1'
#800000
0'
#820000
1'
#840000
0'
#860000
1'
#880000
b10 0
0'
1(
#900000
1$
0!
1"
0%
b10 .
1'
#920000
0'
#940000
1'
#960000
0'
#980000
1%
0!
1"
0$
b1 .
b1 0
1'
0(
#1000000
0'
#1020000
1'
#1040000
0'
#1060000
1'
#1080000
b10 0
0'
1(
#1100000
1$
0!
1"
0%
b10 .
1'
#1120000
0'
#1140000
1'
#1160000
0'
#1180000
1#
1!
0"
0$
b0 .
b0 0
1'
1&
#1200000
0'
#1220000
1'
#1240000
0'
#1260000
1'
#1280000
0'
#1300000
1'
#1320000
0'
#1340000
1'
#1360000
0'
#1380000
0!
1"
1%
0#
b1 .
b10 0
1'
0&
#1400000
0'
#1420000
1$
0!
1"
0%
b10 .
1'
#1440000
0'
#1460000
1'
#1480000
1*
0'
1)
#1500000
1#
1!
0"
0$
b1 0
b0 .
1'
#1520000
0'
#1540000
1'
#1560000
0'
#1580000
0!
1"
1%
0#
b10 0
b1 .
0*
1'
0)
#1600000
0'
#1620000
1$
0!
1"
0%
b10 .
1'
